chrispytools/__init__.py
chrispytools/plot/BarHPlot.py
chrispytools/plot/BarPlot.py
chrispytools/plot/BoxPlot.py
chrispytools/plot/FillPlot.py
chrispytools/plot/HistogramPlot.py
chrispytools/plot/LinePlot.py
chrispytools/plot/LinearPlot.py
chrispytools/plot/PseudoColorPlot.py
chrispytools/plot/SemiLogXPlot.py
chrispytools/plot/SemiLogYPlot.py
chrispytools/plot/__init__.py
chrispytools/plot/base.py
chrispytools/signalprocessing/DigitalizeData.py
chrispytools/signalprocessing/MovingFilter.py
chrispytools/signalprocessing/__init__.py
chrispytools/utils/EngNot.py
chrispytools/utils/ProgressBar.py
chrispytools/utils/__init__.py
chrispytools-0.2.dist-info/licenses/LICENSE.txt
chrispytools-0.2.dist-info/METADATA
chrispytools-0.2.dist-info/WHEEL
chrispytools-0.2.dist-info/top_level.txt
chrispytools-0.2.dist-info/RECORD
