Metadata-Version: 2.4
Name: chrispytools
Version: 0.2
Summary: ChrisPyTools is a set of tools and functions that can be used to quickly plot and analyze data.
Home-page: https://github.com/ChrisHoyer/ChrisPyTools.git
Author: Chris Hoyer
Author-email: info@chrishoyer.de
Requires-Python: >=3.7
License-File: LICENSE.txt
Dynamic: author
Dynamic: author-email
Dynamic: description
Dynamic: description-content-type
Dynamic: home-page
Dynamic: license-file
Dynamic: requires-python
Dynamic: summary
